	[
	  {
	    "id": 15,
	    "name": "รหัส-F15",
	    "linkshopee": "https://s.shopee.co.th/9f60oBtGw2"
	  },
	  {
	    "id": 14,
	    "name": "รหัส-F14",
	    "linkshopee": "https://s.shopee.co.th/4L4USMZULh"
	  },
	  {
	    "id": 13,
	    "name": "รหัส-F13",
	    "linkshopee": "https://s.shopee.co.th/3LBxGU4yTB"
	  },
	  {
	    "id": 12,
	    "name": "รหัส-F12",
	    "linkshopee": "https://s.shopee.co.th/5Kx1e7yAV9"
	  },
	  {
	    "id": 11,
	    "name": "รหัส-F11",
	    "linkshopee": "https://s.shopee.co.th/40Re3e94RE"
	  },
	  {
	    "id": 10,
	    "name": "รหัส-F10",
	    "linkshopee": "https://s.shopee.co.th/8pWtoUrTik"
	  },
	  {
	    "id": 9,
	    "name": "รหัส-F09",
	    "linkshopee": "https://s.shopee.co.th/9UmabgxzvR"
	  },
	  {
	    "id": 8,
	    "name": "รหัส-F08",
	    "linkshopee": "https://s.shopee.co.th/6V8z29J1fR"
	  },
	  {
	    "id": 7,
	    "name": "รหัส-F07",
	    "linkshopee": "https://s.shopee.co.th/1B7SgIaPtD"
	  },
	  {
	    "id": 6,
	    "name": "รหัส-F06",
	    "linkshopee": "https://s.shopee.co.th/6plpQe7nWr"
	  },
	  {
	    "id": 5,
	    "name": "รหัส-F05",
	    "linkshopee": "https://s.shopee.co.th/4L4US1DAoK"
	  },
	  {
	    "id": 4,
	    "name": "รหัส-F04",
	    "linkshopee": "https://s.shopee.co.th/8Uu3Pd7BX1"
	  },
	  {
	    "id": 3,
	    "name": "รหัส-F03",
	    "linkshopee": "https://s.shopee.co.th/3LBxG6b0le"
	  },
	  {
	    "id": 2,
	    "name": "รหัส-F02",
	    "linkshopee": "https://s.shopee.co.th/9f60nckrUQ"
	  },
	  {
	    "id": 1,
	    "name": "รหัส-F01",
	    "linkshopee": "https://s.shopee.co.th/40Re3GWAeC"
	  }
	]